sdnist/__init__.py
sdnist/__main__.py
sdnist/load.py
sdnist/schema.py
sdnist/strs.py
sdnist/utils.py
sdnist/version.py
sdnist/challenge/__init__.py
sdnist/challenge/baseline.py
sdnist/challenge/submission.py
sdnist/challenge/subsample.py
sdnist/metrics/__init__.py
sdnist/metrics/apparent_match_dist.py
sdnist/metrics/graph_edge_map.py
sdnist/metrics/hoc.py
sdnist/metrics/inconsistency.py
sdnist/metrics/kmarg_old.py
sdnist/metrics/kmarginal.py
sdnist/metrics/pca.py
sdnist/metrics/pearson_correlation.py
sdnist/metrics/propensity.py
sdnist/metrics/regression.py
sdnist/metrics/unique_exact_matches.py
sdnist/preprocess/__init__.py
sdnist/report/__init__.py
sdnist/report/__main__.py
sdnist/report/common.py
sdnist/report/config.json
sdnist/report/generate.py
sdnist/report/report_data.py
sdnist/report/server.py
sdnist/report/dataset/__init__.py
sdnist/report/dataset/binning.py
sdnist/report/dataset/transform.py
sdnist/report/dataset/validate.py
sdnist/report/plots/__init__.py
sdnist/report/plots/apparent_match_dist.py
sdnist/report/plots/correlation.py
sdnist/report/plots/grid.py
sdnist/report/plots/pearson_correlation.py
sdnist/report/plots/propensity.py
sdnist/report/plots/univariate.py
sdnist/report/resources/templates/main.jinja2
sdnist/report/score/__init__.py
sdnist/report/score/paragraphs.py
sdnist/report/score/privacy.py
sdnist/report/score/utility/__init__.py
sdnist/report/score/utility/inconsistency.py
sdnist/report/score/utility/linear_regression.py
sdnist/report/score/utility/pca.py
sdnist/visualizer_resources/report2.jinja2
sdnist-2.4.dist-info/LICENSE
sdnist-2.4.dist-info/METADATA
sdnist-2.4.dist-info/WHEEL
sdnist-2.4.dist-info/top_level.txt
sdnist-2.4.dist-info/RECORD
