Metadata-Version: 2.1
Name: sdnist
Version: 2.4
Summary: SDNist: Deidentified Data Report Generator
Home-page: https://github.com/usnistgov/SDNist
Author: National Institute of Standards and Technology
Author-email: gary.howarth@nist.gov
Classifier: Development Status :: 5 - Production/Stable
Classifier: Programming Language :: Python :: 3.8
Classifier: License :: Public Domain
Classifier: Intended Audience :: Science/Research
License-File: LICENSE
Requires-Dist: jinja2 (==3.1.2)
Requires-Dist: loguru (==0.7.0)
Requires-Dist: matplotlib (==3.7.1)
Requires-Dist: numpy (==1.24.2)
Requires-Dist: pandas (==2.0.0)
Requires-Dist: pyarrow (==11.0.0)
Requires-Dist: requests (==2.31.0)
Requires-Dist: scikit-learn (==1.2.2)
Requires-Dist: scipy (==1.10.1)
Requires-Dist: tqdm (==4.65.0)
Requires-Dist: colorama (==0.4.6)
